dima_sdk/__init__.py
dima_sdk/api_client.py
dima_sdk/api_response.py
dima_sdk/configuration.py
dima_sdk/exceptions.py
dima_sdk/py.typed
dima_sdk/rest.py
dima_sdk/api/__init__.py
dima_sdk/api/people_api.py
dima_sdk/models/__init__.py
dima_sdk/models/api_error.py
dima_sdk/models/api_error_container.py
dima_sdk/models/api_error_request.py
dima_sdk/models/get_people200_response.py
dima_sdk/models/get_people_list200_response.py
dima_sdk/models/get_people_list200_response_data_inner.py
dima_sdk/models/get_people_list200_response_data_inner_addresses_inner.py
dima_sdk/models/get_people_list200_response_data_inner_department.py
dima_sdk/models/get_people_list200_response_data_inner_direct_manager.py
dima_sdk/models/get_people_list200_response_data_inner_direct_reports_inner.py
dima_sdk/models/get_people_list200_response_data_inner_emails_inner.py
dima_sdk/models/get_people_list200_response_data_inner_employments_inner.py
dima_sdk/models/get_people_list200_response_data_inner_employments_inner_client_legal_entity.py
dima_sdk/models/get_people_list200_response_data_inner_employments_inner_payment.py
dima_sdk/models/get_people_list200_response_data_inner_employments_inner_team.py
dima_sdk/models/get_people_list200_response_page.py
dima_sdk-2.0.4.dist-info/METADATA
dima_sdk-2.0.4.dist-info/WHEEL
dima_sdk-2.0.4.dist-info/top_level.txt
dima_sdk-2.0.4.dist-info/RECORD
